{
  "contentId": "BILAN_TIP_011",
  "type": "quicktip",
  "topic": "clima-calor",
  "category": "tips",
  "tip": "En climas cálidos puedes perder más de 2 litros de sudor por hora",
  "reason": "El calor extremo dispara tu sudoración para enfriarte. Si solo repones agua, pierdes electrolitos críticos y tu rendimiento colapsa",
  "cta": "Combate el calor",
  "title": "Hidratación en Calor Extremo",
  "subtitle": "Cuando el sudor no para",
  "keyPoint1": "PÉRDIDA\nHasta 2L+ por hora",
  "keyPoint2": "ELECTROLITOS\n1000-2000mg sodio perdido",
  "keyPoint3": "REPOSICIÓN\nAgua + electrolitos cada 20 min",
  "conclusion": "bilan te mantiene funcionando en el calor",
  "hashtags": {
    "tiktok": [
      "#calor",
      "#bilan",
      "#verano",
      "#hidratacion",
      "#sudor"
    ],
    "instagram": [
      "#CalorExtremo",
      "#HidratacionVerano",
      "#Bilan",
      "#Summer"
    ],
    "twitter": [
      "#calor",
      "#verano",
      "#hidratacion"
    ],
    "whatsapp": []
  }
}
